cmemsapi/__init__.py
cmemsapi/cmemsapi.py
cmemsapi-0.1.17.dist-info/AUTHORS.rst
cmemsapi-0.1.17.dist-info/LICENSE
cmemsapi-0.1.17.dist-info/METADATA
cmemsapi-0.1.17.dist-info/WHEEL
cmemsapi-0.1.17.dist-info/entry_points.txt
cmemsapi-0.1.17.dist-info/top_level.txt
cmemsapi-0.1.17.dist-info/RECORD
