Metadata-Version: 2.1
Name: cmemsapi
Version: 0.1.17
Summary: A package to help generating reliable data requests about earth observation and marine related information from Copernicus Marine Database.
Home-page: https://github.com/copernicusmarine/cmemsapi
Author: E.U. Copernicus Marine Service Information
Author-email: servicedesk.cmems@mercator-ocean.eu
License: MIT
Keywords: cmemsapi
Platform: UNKNOWN
Classifier: Development Status :: 2 - Pre-Alpha
Classifier: Intended Audience :: Science/Research
Classifier: License :: OSI Approved :: MIT License
Classifier: Operating System :: OS Independent
Classifier: Natural Language :: English
Classifier: Programming Language :: Python :: 3.6
Classifier: Programming Language :: Python :: 3.7
Classifier: Programming Language :: Python :: 3.8
Classifier: Topic :: Scientific/Engineering
Requires-Python: >=3.6
Requires-Dist: dask
Requires-Dist: fire
Requires-Dist: funcy
Requires-Dist: ipython
Requires-Dist: jedi (<0.18.0)
Requires-Dist: lxml
Requires-Dist: motuclient (==1.8.4)
Requires-Dist: netCDF4 (<=1.5.4)
Requires-Dist: pandas
Requires-Dist: requests
Requires-Dist: scipy
Requires-Dist: toolz
Requires-Dist: xarray
